journal_styles/__init__.py
journal_styles/__main__.py
journal_styles/constants.py
journal_styles/figures.py
journal_styles/parameters.py
journal_styles/styles/Nature.mplstyle
journal_styles/styles/Nature_Comm.mplstyle
journal_styles/styles/PR.mplstyle
journal_styles/styles/Science.mplstyle
journal_styles/styles/__init__.py
journal_styles/styles/matplotlibrc
journal_styles-1.1.0.dist-info/LICENSE.txt
journal_styles-1.1.0.dist-info/METADATA
journal_styles-1.1.0.dist-info/WHEEL
journal_styles-1.1.0.dist-info/RECORD
