Metadata-Version: 2.1
Name: journal-styles
Version: 1.1.0
Summary: Package for producing consistent figure dimensions for scientific journals
License: MIT
Author: Iacopo Torre
Author-email: iacopo.torre@upc.edu
Requires-Python: >=3.9,<4.0
Classifier: License :: OSI Approved :: MIT License
Classifier: Programming Language :: Python :: 3
Classifier: Programming Language :: Python :: 3.9
Classifier: Programming Language :: Python :: 3.10
Classifier: Programming Language :: Python :: 3.11
Classifier: Programming Language :: Python :: 3.12
Requires-Dist: matplotlib (>=3,<4)
Requires-Dist: numpy (>=1.26,<2.0)
